calculator/__init__.py
muzaffarsmartcalc-1.0.1.dist-info/LICENCE
muzaffarsmartcalc-1.0.1.dist-info/METADATA
muzaffarsmartcalc-1.0.1.dist-info/WHEEL
muzaffarsmartcalc-1.0.1.dist-info/top_level.txt
muzaffarsmartcalc-1.0.1.dist-info/RECORD
